intake_awkward/__init__.py
intake_awkward/_version.py
intake_awkward/json.py
intake_awkward/py.typed
intake_awkward-0.0.1.dist-info/LICENSE
intake_awkward-0.0.1.dist-info/METADATA
intake_awkward-0.0.1.dist-info/WHEEL
intake_awkward-0.0.1.dist-info/entry_points.txt
intake_awkward-0.0.1.dist-info/top_level.txt
intake_awkward-0.0.1.dist-info/RECORD
