Metadata-Version: 2.1
Name: intake-awkward
Version: 0.0.1
Summary: Intake for Awkward
Author: Doug Davis
Author-email: ddavis@ddavis.io
Maintainer: Doug Davis
Maintainer-email: ddavis@ddavis.io
License: BSD-3-Clause
Platform: UNKNOWN
Classifier: Intended Audience :: Science/Research
Classifier: License :: OSI Approved :: BSD License
Classifier: Programming Language :: Python :: 3
Classifier: Programming Language :: Python :: 3 :: Only
Classifier: Programming Language :: Python :: 3.8
Classifier: Programming Language :: Python :: 3.9
Classifier: Programming Language :: Python :: 3.10
Classifier: Topic :: Scientific/Engineering
Requires-Python: >=3.8
License-File: LICENSE
Requires-Dist: dask-awkward (>=2022.3a0)
Requires-Dist: intake (>=0.6.5)
Provides-Extra: complete
Requires-Dist: pytest (>=6.0) ; extra == 'complete'
Provides-Extra: test
Requires-Dist: pytest (>=6.0) ; extra == 'test'
